src/defines.v
// File: src/defines.v
// Description: Constants for RISC CPU opcodes and controller states

`ifndef DEFINES_V
`define DEFINES_V

// Opcode definitions (3-bit)
`define OPCODE_HLT  3'b000  // Halt
`define OPCODE_SKZ  3'b001  // Skip if zero
`define OPCODE_ADD  3'b010  // Add
`define OPCODE_AND  3'b011  // Bitwise AND
`define OPCODE_XOR  3'b100  // Bitwise XOR
`define OPCODE_LDA  3'b101  // Load Accumulator
`define OPCODE_STO  3'b110  // Store Accumulator
`define OPCODE_JMP  3'b111  // Jump

// Controller state encodings (3-bit)
`define STATE_INST_ADDR  3'd0  // Instruction address
`define STATE_INST_FETCH 3'd1  // Instruction fetch
`define STATE_INST_LOAD  3'd2  // Instruction load
//`define STATE_IDLE       3'd3  // Idle
`define STATE_OP_ADDR    3'd3  // Operand address
`define STATE_OP_FETCH   3'd4  // Operand fetch
`define STATE_ALU_OP     3'd5  // ALU operation
`define STATE_STORE      3'd6  // Store
`define STATE_NEXT       3'd7   
`endif

src/memory.v
// File: src/memory.v
// Description: 32x8-bit Memory for RISC CPU
`timescale 1ns/1ps

module memory (
    input  wire        clk,
    input  wire        rst,
    input  wire [4:0]  addr,
    input  wire [7:0]  data_in,
    output reg  [7:0]  data_out,
    input  wire        rd,
    input  wire        wr
);
    reg [7:0] mem [0:31];

    always @(posedge clk) begin
        if (rst) begin
            $readmemh("tb/test_programs/test3.mem", mem);
        end
    end


    // Combinational read
    always @(*) begin
        if (rd)
            data_out = mem[addr];
        else
            data_out = 8'b0;
    end

    // Synchronous write
    always @(posedge clk) begin
        if (wr)
            mem[addr] <= data_in;
    end
endmodule

src/register.v
// File: src/register.v
// Description: 8-bit Accumulator for RISC CPU
`timescale 1ns/1ps

module register (
    input wire clk,
    input wire rst,
    input wire load,
    input wire [7:0] in,
    output reg [7:0] out
);
    always @(posedge clk or posedge rst) begin
        if (rst)
            out <= 8'b0;
        else if (load)
            out <= in;
    end
endmodule

src/controller.v
// File: src/controller.v
// Description: Controller for RISC CPU with 8 states
// Includes defines.v for opcode and state constants

`timescale 1ns/1ps
`include "src/defines.v"

module controller (
    input wire        clk,
    input wire        rst,
    input wire [2:0]  opcode,
    input wire        zero,
    output reg        sel,
    output reg        rd,
    output reg        ld_ir,
    output reg        halt,
    output reg [1:0]  inc_pc,
    output reg        ld_ac,
    output reg        ld_pc,
    output reg        wr,
    output reg        data_e,
    output reg [2:0] state
);

    reg skip_next;

    // Sequential logic (partial)
    always @(posedge clk or posedge rst) begin
        if (rst) begin
            sel <= 0; rd <= 0; ld_ir <= 0; halt <= 0;
            inc_pc <= 0; ld_ac <= 0; ld_pc <= 0; wr <= 0; data_e <= 0;
            skip_next <= 0;
            state <= `STATE_INST_ADDR;
        end else if (halt) begin
            rd <= 0; ld_ir <= 0; inc_pc <= 0;
        end else begin
            case (state)
                `STATE_INST_ADDR: state <= `STATE_INST_FETCH;
                `STATE_INST_FETCH: state <= `STATE_INST_LOAD;
                `STATE_INST_LOAD: state <= `STATE_OP_ADDR;
                `STATE_OP_ADDR: state <= `STATE_OP_FETCH;
                `STATE_OP_FETCH: state <= `STATE_ALU_OP;
                `STATE_ALU_OP: state <= `STATE_STORE;
                `STATE_STORE: state <= `STATE_NEXT;
                `STATE_NEXT: begin
                    if (skip_next) state <= `STATE_INST_ADDR; // Skip next instruction
                    else state <= `STATE_INST_ADDR; // Normal progression
                end
                default: state <= `STATE_INST_ADDR; // Reset to initial state if undefined
            endcase

            // Handle opcode-specific logic
            case (state)
                `STATE_ALU_OP: begin
                    ld_ac <= (opcode == `OPCODE_ADD || opcode == `OPCODE_AND ||
                            opcode == `OPCODE_XOR || opcode == `OPCODE_LDA);
                    skip_next <= (opcode == `OPCODE_SKZ && zero);
                    ld_pc <= (opcode == `OPCODE_JMP);
                    if (opcode == `OPCODE_SKZ)
                        $display("SKZ: zero=%b, skip_next=%b at time %t", zero, (opcode == `OPCODE_SKZ && zero), $time);
                end
                `STATE_STORE: begin
                    ld_ac <= 0;
                end
                default: begin
                    ld_ac <= 0;
                    skip_next <= 0;
                end
            endcase
        end
    end

    // Combinational logic (partial)
    always @(*) begin
        sel = 0; rd = 0; ld_ir = 0; halt = 0; inc_pc = 0;
        ld_pc = 0; wr = 0; data_e = 0;

        halt = (opcode == `OPCODE_HLT);

        case (state)
            `STATE_INST_ADDR: begin
                sel = 1;
            end
            `STATE_INST_FETCH: begin
                sel = 1;
                rd = 1;
            end
            `STATE_INST_LOAD: begin
                sel = 1;
                rd = 1;
                ld_ir = 1;
            end
            `STATE_OP_ADDR: begin
                sel = 0;
            end
            `STATE_OP_FETCH: begin
                sel = 0;
                rd = 1;
            end
            `STATE_ALU_OP: begin
                ld_pc = (opcode == `OPCODE_JMP);
            end
            `STATE_STORE: begin
                wr = (opcode == `OPCODE_STO);
                data_e = (opcode == `OPCODE_STO);
                sel = 0;
            end
            `STATE_NEXT: begin
                if (skip_next) begin
                    inc_pc = 2;
                    $display("SKZ: Skipping next instruction, inc_pc set to 2 at time %t", $time);
                end else if (!halt) begin
                    inc_pc = 1; // Ensure PC increments for valid instructions
                end
            end
            default: begin
                halt = 1; // Halt on undefined state as a fallback
            end
        endcase
    end

endmodule

src/alu.v
// File: src/alu.v
// Description: ALU for RISC CPU with 8 operations
// Includes defines.v for opcode constants
`timescale 1ns/1ps
`include "src/defines.v"

module alu (
    input  wire [2:0] opcode,    // 3-bit opcode
    input  wire [7:0]  inA,       // 8-bit input A (Accumulator)
    input  wire [7:0]  inB,       // 8-bit input B (Memory)
    output reg  [7:0]  out,       // 8-bit output
    output wire   is_zero    // Asynchronous zero flag
);
    // Combinational ALU operations
    always @(*) begin
        case (opcode)
            `OPCODE_HLT:  out = inA;                // Halt: pass inA
            `OPCODE_SKZ:  out = inA;                // Skip if zero: pass inA
            `OPCODE_ADD:  out = inA + inB;          // Add
            `OPCODE_AND:  out = inA & inB;          // Bitwise AND
            `OPCODE_XOR:  out = inA ^ inB;          // Bitwise XOR
            `OPCODE_LDA:  out = inB;                // Load Accumulator
            `OPCODE_STO:  out = inA;                // Store: pass inA
            `OPCODE_JMP:  out = inA;                // Jump: pass inA
            default:      out = 8'b0;               // Default: 0
        endcase
    end

    assign is_zero = (inA == 8'b0);
endmodule

src/address_mux.v
// File: src/address_mux.v
// Description: 5-bit Address Mux for RISC CPU
`timescale 1ns/1ps

module address_mux #(
    parameter WIDTH = 5
) (
    input  wire             sel,        // Select: 1=instruction, 0=operand
    input  wire [WIDTH-1:0] inst_addr,  // Instruction address (from PC)
    input  wire [WIDTH-1:0] op_addr,    // Operand address (from instruction)
    output wire [WIDTH-1:0] addr        // Selected address
);

    assign addr = sel ? inst_addr : op_addr;

endmodule

src/program_counter.v
// File: src/program_counter.v
// Description: 5-bit Program Counter for RISC CPU
`timescale 1ns/1ps

module program_counter (
    input  wire        clk,
    input  wire        rst,
    input  wire        load,
    input  wire [1:0]  inc_pc,  // 2 bits: 0 = no increment, 1 = +1, 2 = +2
    input  wire [4:0]  load_val,
    output reg  [4:0]  pc
);

    always @(posedge clk or posedge rst) begin
        if (rst)
            pc <= 0;
        else if (load)
            pc <= load_val;
        else if (inc_pc == 2)
            pc <= pc + 2;  // Skip next instruction
        else if (inc_pc == 1)
            pc <= pc + 1;  // Normal increment
    end
endmodule

src/risc_cpu.v
// File: src/risc_cpu.v
// Description: Top-level RISC CPU module
// Includes defines.v for opcode constants
`timescale 1ns/1ps

`include "src/defines.v"
`include "src/program_counter.v"
`include "src/address_mux.v"
`include "src/alu.v"
`include "src/controller.v"
`include "src/register.v"
`include "src/memory.v"

module risc_cpu (
    input  wire        clk,        // Clock input
    input  wire        rst,        // Reset input
    output wire [7:0]  data_out,   // Accumulator output
    output wire [7:0]  data_in_out // Expose data_in for monitoring
);

    // Internal signals
    wire [4:0] pc;                // Program Counter
    wire [4:0] addr;              // Memory address
    wire [7:0] alu_out;           // ALU output
    wire [7:0] reg_out;           // Accumulator output
    wire [7:0] mem_out;           // Memory output
    wire [2:0] opcode;            // 3-bit opcode
    wire sel, rd, ld_ir, halt, ld_ac, ld_pc, wr, data_e, zero;

    wire [7:0] data_in;
    // Add data register to latch memory output
    reg [7:0] data_reg;
    wire [7:0] alu_inB;           // ALU input B (from data_reg)

    // Module instantiations
    wire [1:0] inc_pc;  

    // Local state wire (if not directly accessible)
    wire [2:0] state;

    // Instruction register
    reg [7:0] ir;


    program_counter pc0 (
        .clk(clk),
        .rst(rst),
        .load(ld_pc),
        .inc_pc(inc_pc),  // Now 2 bits
        .load_val(ir[4:0]),
        .pc(pc)
    );
    always @(posedge clk or posedge rst) begin
        if (rst)
            ir <= 8'b10100000;  // Non-HLT opcode
        else if (ld_ir) begin
            ir <= mem_out;
            $display("IR updated to %h (ir[4:0]=%b) at time %t", mem_out, mem_out[4:0], $time);
        end
    end

    address_mux mux0 (
        .sel(sel),
        .inst_addr(pc),
        .op_addr(ir[4:0]),
        .addr(addr)
    );

    alu alu0 (
        .opcode(opcode),
        .inA(reg_out),
        .inB(alu_inB),
        .out(alu_out),
        .is_zero(zero)
    );
    always @(zero) $display("Zero signal updated to %b at time %t", zero, $time);

    controller ctrl0 (
        .clk(clk),
        .rst(rst),
        .opcode(opcode),
        .zero(zero),
        .sel(sel),
        .rd(rd),
        .ld_ir(ld_ir),
        .halt(halt),
        .inc_pc(inc_pc),
        .ld_ac(ld_ac),
        .ld_pc(ld_pc),
        .wr(wr),
        .data_e(data_e),
        .state(state)  // Add state output
    );

    register reg0 (
        .clk(clk),
        .rst(rst),
        .load(ld_ac),
        .in(alu_out),
        .out(reg_out)
    );
    //debug accumulator
    always @(posedge clk) begin
        if (ld_ac)
            $display("Accumulator updated to %h at time %t", alu_out, $time);
    end


    memory mem0 (
        .clk(clk),
        .addr(addr),
        .data_in(data_in),
        .data_out(mem_out),
        .rd(rd),
        .wr(wr),
        .rst(rst)
    );

    
    // always @(posedge clk or posedge rst) begin
    //     if (rst)
    //         ir <= 8'b10100000;  // Non-HLT opcode
    //     else if (ld_ir)
    //         ir <= mem_out;
    // end

    // Extract opcode
    assign opcode = ir[7:5];
    assign data_out = reg_out;

    // Data input for memory
    assign data_in = data_e ? reg_out : 8'b0;
    assign data_in_out = data_in;

    // Latch memory data one cycle after STATE_OP_FETCH
    reg [2:0] prev_state;
    always @(posedge clk or posedge rst) begin
        if (rst) begin
            data_reg <= 8'b0;
            prev_state <= 0;
        end else begin
            prev_state <= state;
            if (state == `STATE_OP_FETCH)  // Capture during STATE_OP_FETCH
                data_reg <= mem_out;
        end
    end

    //debug data reg
    always @(posedge clk) begin
        if (state == `STATE_OP_FETCH)
            $display("STATE_OP_FETCH: mem_out=%h, Data_reg=%h at time %t", mem_out, data_reg, $time);
    end

    // Assign ALU input B from data_reg
    assign alu_inB = data_reg;

    

endmodule

tb/risc_cpu_tb.v

// Description: Testbench for RISC CPU module
`timescale 1ns/1ps
`include "src/risc_cpu.v"

module tb_risc_cpu;

    integer i;
    // Inputs
    reg clk;
    reg rst;

    // Outputs
    wire [7:0] data_out;

    // Instantiate RISC CPU
    risc_cpu uut (
        .clk(clk),
        .rst(rst),
        .data_out(data_out)
    );

    // Clock generation
    initial begin
        clk = 0;
        forever #5 clk = ~clk;  // 10ns period (100 MHz)
    end

    // Test stimulus
    initial begin
        // Reset
        rst = 1;
        #200;
        rst = 0;

        // Load memory with test1.mem or test2.mem
        //$readmemb("tb/test_programs/test1.mem", uut.mem0.mem);  // For test1.mem
        $readmemh("tb/test_programs/test3.mem", uut.mem0.mem);  // For test2.mem use hex format
        
        // Debug: Print memory contents to verify initialization
        #10;
        for (i = 0; i < 10; i = i+1) begin
            $display("Mem[%d] = %h at time %t", i, uut.mem0.mem[i], $time);
        end


        // Run simulation for a fixed time
        #1000;

        // Check results
        $display("Final Accumulator value: %h", data_out);
        $display("Memory at address 7: %h", uut.mem0.mem[7]);  // For test1.mem
        $finish;
    end

    //debug monitor
    initial begin
        $monitor("Time=%0t rst=%b clk=%b PC=%d State=%d IR=%h Opcode=%b Wr=%b Data_e=%b Sel=%b Addr=%h Data_in=%h Data_reg=%h Accumulator=%h Mem[7]=%h Ld_ac=%b Alu_out=%h",
            $time, rst, clk, uut.pc, uut.ctrl0.state, uut.ir, uut.opcode, uut.wr,
            uut.data_e, uut.sel, uut.addr, uut.data_in_out, uut.data_reg,
            data_out, uut.mem0.mem[7], uut.ctrl0.ld_ac, uut.alu0.out);   
    end
    
    // Dump waveform for Cadence
    initial begin
        $dumpfile("sim/waveform.vcd");
        $dumpvars(0, tb_risc_cpu);
    end

endmodule

sim/waveform.vcd
$date
	Thu May 08 14:04:31 2025
$end
$version
	Icarus Verilog
$end
$timescale
	1ps
$end
$scope module tb_risc_cpu $end
$var wire 8 ! data_out [7:0] $end
$var reg 1 " clk $end
$var integer 32 # i [31:0] $end
$var reg 1 $ rst $end
$scope module uut $end
$var wire 5 % addr [4:0] $end
$var wire 8 & alu_inB [7:0] $end
$var wire 8 ' alu_out [7:0] $end
$var wire 1 ( clk $end
$var wire 1 ) data_e $end
$var wire 8 * data_in [7:0] $end
$var wire 8 + data_in_out [7:0] $end
$var wire 8 , data_out [7:0] $end
$var wire 1 - halt $end
$var wire 2 . inc_pc [1:0] $end
$var wire 1 / ld_ac $end
$var wire 1 0 ld_ir $end
$var wire 1 1 ld_pc $end
$var wire 8 2 mem_out [7:0] $end
$var wire 3 3 opcode [2:0] $end
$var wire 5 4 pc [4:0] $end
$var wire 1 5 rd $end
$var wire 8 6 reg_out [7:0] $end
$var wire 1 7 rst $end
$var wire 1 8 sel $end
$var wire 3 9 state [2:0] $end
$var wire 1 : wr $end
$var wire 1 ; zero $end
$var reg 8 < data_reg [7:0] $end
$var reg 8 = ir [7:0] $end
$var reg 3 > prev_state [2:0] $end
$scope module pc0 $end
$var wire 1 ( clk $end
$var wire 2 ? inc_pc [1:0] $end
$var wire 1 1 load $end
$var wire 5 @ load_val [4:0] $end
$var wire 1 7 rst $end
$var reg 5 A pc [4:0] $end
$upscope $end
$scope module mux0 $end
$var wire 5 B addr [4:0] $end
$var wire 5 C inst_addr [4:0] $end
$var wire 5 D op_addr [4:0] $end
$var wire 1 8 sel $end
$upscope $end
$scope module alu0 $end
$var wire 8 E inA [7:0] $end
$var wire 8 F inB [7:0] $end
$var wire 1 ; is_zero $end
$var wire 3 G opcode [2:0] $end
$var reg 8 H out [7:0] $end
$upscope $end
$scope module ctrl0 $end
$var wire 1 ( clk $end
$var wire 3 I opcode [2:0] $end
$var wire 1 7 rst $end
$var wire 1 ; zero $end
$var reg 1 J data_e $end
$var reg 1 K halt $end
$var reg 2 L inc_pc [1:0] $end
$var reg 1 M ld_ac $end
$var reg 1 N ld_ir $end
$var reg 1 O ld_pc $end
$var reg 1 P rd $end
$var reg 1 Q sel $end
$var reg 1 R skip_next $end
$var reg 3 S state [2:0] $end
$var reg 1 T wr $end
$upscope $end
$scope module reg0 $end
$var wire 1 ( clk $end
$var wire 8 U in [7:0] $end
$var wire 1 / load $end
$var wire 1 7 rst $end
$var reg 8 V out [7:0] $end
$upscope $end
$scope module mem0 $end
$var wire 5 W addr [4:0] $end
$var wire 1 ( clk $end
$var wire 8 X data_in [7:0] $end
$var wire 1 5 rd $end
$var wire 1 7 rst $end
$var wire 1 : wr $end
$var reg 8 Y data_out [7:0] $end
$upscope $end
$upscope $end
$upscope $end
$enddefinitions $end
#0
$dumpvars
b0 Y
b0 X
b0 W
b0 V
b0 U
0T
b0 S
0R
1Q
0P
0O
0N
0M
b0 L
0K
0J
b101 I
b0 H
b101 G
b0 F
b0 E
b0 D
b0 C
b0 B
b0 A
b0 @
b0 ?
b0 >
b10100000 =
b0 <
1;
0:
b0 9
18
17
b0 6
05
b0 4
b101 3
b0 2
01
00
0/
b0 .
0-
b0 ,
b0 +
b0 *
0)
0(
b0 '
b0 &
b0 %
1$
bx #
0"
b0 !
$end
#5000
0Q
08
1"
1(
#10000
0"
0(
#15000
1"
1(
#20000
0"
0(
#25000
1"
1(
#30000
0"
0(
#35000
1"
1(
#40000
0"
0(
#45000
1"
1(
#50000
0"
0(
#55000
1"
1(
#60000
0"
0(
#65000
1"
1(
#70000
0"
0(
#75000
1"
1(
#80000
0"
0(
#85000
1"
1(
#90000
0"
0(
#95000
1"
1(
#100000
0"
0(
#105000
1"
1(
#110000
0"
0(
#115000
1"
1(
#120000
0"
0(
#125000
1"
1(
#130000
0"
0(
#135000
1"
1(
#140000
0"
0(
#145000
1"
1(
#150000
0"
0(
#155000
1"
1(
#160000
0"
0(
#165000
1"
1(
#170000
0"
0(
#175000
1"
1(
#180000
0"
0(
#185000
1"
1(
#190000
0"
0(
#195000
1"
1(
#200000
0"
0(
0$
07
#205000
b11111110 Y
b11111110 2
1P
15
1Q
18
b1 S
b1 9
1"
1(
#210000
0"
0(
b1010 #
#215000
1N
10
1P
15
1Q
18
b10 S
b10 9
b1 >
1"
1(
#220000
0"
0(
#225000
b0 Y
b0 2
b11110 %
b11110 B
b11110 W
b11110 @
b11110 D
b111 3
b111 G
b111 I
0N
00
0P
05
0Q
08
b10 >
b11111110 =
b11 S
b11 9
1"
1(
#230000
0"
0(
#235000
1P
15
b100 S
b100 9
b11 >
1"
1(
#240000
0"
0(
#245000
1O
11
0P
05
b100 >
b101 S
b101 9
1"
1(
#250000
0"
0(
#255000
0O
01
b11110 A
b11110 4
b11110 C
b110 S
b110 9
b101 >
1"
1(
#260000
0"
0(
#265000
b1 L
b1 .
b1 ?
b110 >
b111 S
b111 9
1"
1(
#270000
0"
0(
#275000
b11111 %
b11111 B
b11111 W
1Q
18
b0 L
b0 .
b0 ?
b11111 A
b11111 4
b11111 C
b0 S
b0 9
b111 >
1"
1(
#280000
0"
0(
#285000
1P
15
1Q
18
b0 >
b1 S
b1 9
1"
1(
#290000
0"
0(
#295000
1N
10
1P
15
1Q
18
b10 S
b10 9
b1 >
1"
1(
#300000
0"
0(
#305000
1K
1-
b0 %
b0 B
b0 W
b0 @
b0 D
b0 3
b0 G
b0 I
0N
00
0P
05
0Q
08
b10 >
b0 =
b11 S
b11 9
1"
1(
#310000
0"
0(
#315000
b11 >
1"
1(
