src/defines.v
// File: src/defines.v
// Description: Constants for RISC CPU opcodes and controller states

`ifndef DEFINES_V
`define DEFINES_V

// Opcode definitions (3-bit)
`define OPCODE_HLT  3'b000  // Halt
`define OPCODE_SKZ  3'b001  // Skip if zero
`define OPCODE_ADD  3'b010  // Add
`define OPCODE_AND  3'b011  // Bitwise AND
`define OPCODE_XOR  3'b100  // Bitwise XOR
`define OPCODE_LDA  3'b101  // Load Accumulator
`define OPCODE_STO  3'b110  // Store Accumulator
`define OPCODE_JMP  3'b111  // Jump

// Controller state encodings (3-bit)
`define STATE_INST_ADDR  3'd0  // Instruction address
`define STATE_INST_FETCH 3'd1  // Instruction fetch
`define STATE_INST_LOAD  3'd2  // Instruction load
//`define STATE_IDLE       3'd3  // Idle
`define STATE_OP_ADDR    3'd3  // Operand address
`define STATE_OP_FETCH   3'd4  // Operand fetch
`define STATE_ALU_OP     3'd5  // ALU operation
`define STATE_STORE      3'd6  // Store
`define STATE_NEXT       3'd7   
`endif

src/memory.v
// File: src/memory.v
// Description: 32x8-bit Memory for RISC CPU
`timescale 1ns/1ps

module memory (
    input  wire        clk,       // Clock input (rising edge)
    input  wire [4:0]  addr,      // 5-bit address
    input  wire [7:0]  data_in,   // 8-bit input data
    output reg  [7:0]  data_out,  // 8-bit output data
    input  wire        rd,        // Read enable
    input  wire        wr         // Write enable
);

    reg [7:0] mem [0:31];  // 32x8-bit memory array

    always @(posedge clk) begin
        if (wr && !rd) begin
            mem[addr] <= data_in;  // Write data
        end
        if (rd && !wr) begin
            data_out <= mem[addr]; // Read data
        end
    end

endmodule

src/register.v
// File: src/register.v
// Description: 8-bit Accumulator for RISC CPU
`timescale 1ns/1ps

module register (
    input wire clk,
    input wire rst,
    input wire load,
    input wire [7:0] in,
    output reg [7:0] out
);
    always @(posedge clk or posedge rst) begin
        if (rst)
            out <= 8'b0;
        else if (load)
            out <= in;
    end
endmodule

src/controller.v
// File: src/controller.v
// Description: Controller for RISC CPU with 8 states
// Includes defines.v for opcode and state constants

`timescale 1ns/1ps
`include "src/defines.v"

module controller (
    input wire        clk,
    input wire        rst,
    input wire [2:0]  opcode,
    input wire        zero,
    output reg        sel,
    output reg        rd,
    output reg        ld_ir,
    output reg        halt,
    output reg        inc_pc,
    output reg        ld_ac,
    output reg        ld_pc,
    output reg        wr,
    output reg        data_e
);

    reg [2:0] state;

    // State transition and sequential outputs
    always @(posedge clk or posedge rst) begin
        if (rst) begin
            state <= `STATE_INST_ADDR;
            ld_ac <= 0;  // Reset ld_ac
        end else begin
            // State transitions
            if (halt && state == `STATE_NEXT)
                state <= state;
            else
                state <= (state == `STATE_STORE) ? `STATE_NEXT :
                        (state == `STATE_NEXT) ? `STATE_INST_ADDR : state + 1;

            // Sequential control for ld_ac to ensure it holds through the clock edge
            case (state)
                `STATE_ALU_OP: begin
                    ld_ac <= (opcode == `OPCODE_ADD || opcode == `OPCODE_AND ||
                             opcode == `OPCODE_XOR || opcode == `OPCODE_LDA);
                end
                `STATE_STORE: begin
                    ld_ac <= 0;  // Clear ld_ac after ALU operation
                end
                default: begin
                    ld_ac <= 0;
                end
            endcase
        end
    end

    // Output logic (combinational)
    always @(*) begin
        sel = 0; rd = 0; ld_ir = 0; halt = 0; inc_pc = 0;
        ld_pc = 0; wr = 0; data_e = 0;

        halt = (opcode == `OPCODE_HLT);

        case (state)
            `STATE_INST_ADDR: begin
                sel = 1;
            end
            `STATE_INST_FETCH: begin
                sel = 1;
                rd = 1;
            end
            `STATE_INST_LOAD: begin
                sel = 1;
                rd = 1;
                ld_ir = 1;
            end
            `STATE_OP_ADDR: begin
                sel = 0;
            end
            `STATE_OP_FETCH: begin
                sel = 0;
                rd = 1;
            end
            `STATE_ALU_OP: begin
                // Remove rd to avoid re-reading memory; data_reg should be used
                ld_pc = (opcode == `OPCODE_JMP);
            end
            `STATE_STORE: begin
                wr = (opcode == `OPCODE_STO);
                data_e = (opcode == `OPCODE_STO);
                sel = 0;
            end
            `STATE_NEXT: begin
                inc_pc = !halt;
            end
        endcase
    end

endmodule

src/alu.v
// File: src/alu.v
// Description: ALU for RISC CPU with 8 operations
// Includes defines.v for opcode constants
`timescale 1ns/1ps
`include "src/defines.v"

module alu (
    input  wire [2:0] opcode,    // 3-bit opcode
    input  wire [7:0]  inA,       // 8-bit input A (Accumulator)
    input  wire [7:0]  inB,       // 8-bit input B (Memory)
    output reg  [7:0]  out,       // 8-bit output
    output wire   is_zero    // Asynchronous zero flag
);
    // Combinational ALU operations
    always @(*) begin
        case (opcode)
            `OPCODE_HLT:  out = inA;                // Halt: pass inA
            `OPCODE_SKZ:  out = inA;                // Skip if zero: pass inA
            `OPCODE_ADD:  out = inA + inB;          // Add
            `OPCODE_AND:  out = inA & inB;          // Bitwise AND
            `OPCODE_XOR:  out = inA ^ inB;          // Bitwise XOR
            `OPCODE_LDA:  out = inB;                // Load Accumulator
            `OPCODE_STO:  out = inA;                // Store: pass inA
            `OPCODE_JMP:  out = inA;                // Jump: pass inA
            default:      out = 8'b0;               // Default: 0
        endcase
    end

    assign is_zero = (out == 8'b0);
endmodule

src/address_mux.v
// File: src/address_mux.v
// Description: 5-bit Address Mux for RISC CPU
`timescale 1ns/1ps

module address_mux #(
    parameter WIDTH = 5
) (
    input  wire             sel,        // Select: 1=instruction, 0=operand
    input  wire [WIDTH-1:0] inst_addr,  // Instruction address (from PC)
    input  wire [WIDTH-1:0] op_addr,    // Operand address (from instruction)
    output wire [WIDTH-1:0] addr        // Selected address
);

    assign addr = sel ? inst_addr : op_addr;

endmodule

src/program_counter.v
// File: src/program_counter.v
// Description: 5-bit Program Counter for RISC CPU
`timescale 1ns/1ps

module program_counter (
    input wire clk,
    input wire rst,
    input wire load,
    input wire inc_pc,  // Add inc_pc input
    input wire [4:0] load_val,
    output reg [4:0] pc
);

always @(posedge clk or posedge rst) begin
    if (rst)
        pc <= 5'b0;
    else if (load)
        pc <= load_val;
    else if (inc_pc)
        pc <= pc + 1;
end
endmodule

src/risc_cpu.v
// File: src/risc_cpu.v
// Description: Top-level RISC CPU module
// Includes defines.v for opcode constants
`timescale 1ns/1ps

`include "src/defines.v"
`include "src/program_counter.v"
`include "src/address_mux.v"
`include "src/alu.v"
`include "src/controller.v"
`include "src/register.v"
`include "src/memory.v"

module risc_cpu (
    input  wire        clk,        // Clock input
    input  wire        rst,        // Reset input
    output wire [7:0]  data_out,   // Accumulator output
    output wire [7:0]  data_in_out // Expose data_in for monitoring
);

    // Internal signals
    wire [4:0] pc;                // Program Counter
    wire [4:0] addr;              // Memory address
    wire [7:0] alu_out;           // ALU output
    wire [7:0] reg_out;           // Accumulator output
    wire [7:0] mem_out;           // Memory output
    wire [2:0] opcode;            // 3-bit opcode
    wire sel, rd, ld_ir, halt, inc_pc, ld_ac, ld_pc, wr, data_e, zero;

    // Add data register to latch memory output
    reg [7:0] data_reg;
    wire [7:0] alu_inB;           // ALU input B (from data_reg)

    // Module instantiations
    program_counter pc0 (
        .clk(clk),
        .rst(rst),
        .load(ld_pc),
        .inc_pc(inc_pc),
        .load_val(mem_out[4:0]),
        .pc(pc)
    );

    address_mux mux0 (
        .sel(sel),
        .inst_addr(pc),
        .op_addr(ir[4:0]),   // Corrected to use instruction bits
        .addr(addr)
    );

    alu alu0 (
        .opcode(opcode),
        .inA(reg_out),
        .inB(alu_inB),       // Use latched data
        .out(alu_out),
        .is_zero(zero)
    );

    controller ctrl0 (
        .clk(clk),
        .rst(rst),
        .opcode(opcode),
        .zero(zero),
        .sel(sel),
        .rd(rd),
        .ld_ir(ld_ir),
        .halt(halt),
        .inc_pc(inc_pc),
        .ld_ac(ld_ac),
        .ld_pc(ld_pc),
        .wr(wr),
        .data_e(data_e)
    );

    register reg0 (
        .clk(clk),
        .rst(rst),
        .load(ld_ac),
        .in(alu_out),
        .out(reg_out)
    );

    memory mem0 (
        .clk(clk),
        .addr(addr),
        .data_in(data_in),    // Connect to internal data_in
        .data_out(mem_out),
        .rd(rd),
        .wr(wr)
    );

    // Instruction register (simplified)
    reg [7:0] ir;
    always @(posedge clk or posedge rst) begin
        if (rst)
            ir <= 8'b10100000;  // Non-HLT opcode
        else if (ld_ir)
            ir <= mem_out;
    end

    // Extract opcode from instruction
    assign opcode = ir[7:5];  // 3-bit opcode (bits 7:5)
    assign data_out = reg_out; // Output Accumulator

    // Assign data_in based on data_e
    wire [7:0] data_in = data_e ? reg_out : 8'b0;
    assign data_in_out = data_in; // Expose data_in as output

    // Latch memory data in STATE_OP_FETCH
    always @(posedge clk or posedge rst) begin
        if (rst)
            data_reg <= 8'b0;
        else if (ctrl0.state == `STATE_OP_FETCH)  // Assuming state is accessible
            data_reg <= mem_out;
    end

    // Assign ALU input B from data_reg
    assign alu_inB = data_reg;

endmodule

tb/risc_cpu_tb.v

// Description: Testbench for RISC CPU module
`timescale 1ns/1ps
`include "src/risc_cpu.v"

module tb_risc_cpu;

    // Inputs
    reg clk;
    reg rst;

    // Outputs
    wire [7:0] data_out;

    // Instantiate RISC CPU
    risc_cpu uut (
        .clk(clk),
        .rst(rst),
        .data_out(data_out)
    );

    // Clock generation
    initial begin
        clk = 0;
        forever #5 clk = ~clk;  // 10ns period (100 MHz)
    end

    // Test stimulus
    initial begin
        // Reset
        rst = 1;
        #20;
        rst = 0;

        // Load memory with test1.mem or test2.mem
        // Comment/uncomment to switch between test programs
        $readmemb("tb/test_programs/test1.mem", uut.mem0.mem);  // For test1.mem
        // $readmemb("tb/test_programs/test2.mem", uut.mem0.mem);  // For test2.mem

        // Run simulation for a fixed time
        #1000;

        // Check results
        $display("Final Accumulator value: %h", data_out);
        $display("Memory at address 7: %h", uut.mem0.mem[7]);  // For test1.mem
        $finish;
    end

    //debug purposes
    initial begin
        $monitor("Time=%0t rst=%b clk=%b PC=%d State=%d IR=%h Opcode=%b Wr=%b Data_e=%b Sel=%b Addr=%h Data_in=%h Data_reg=%h Accumulator=%h Mem[7]=%h Ld_ac=%b Alu_out=%h",
            $time, rst, clk, uut.pc, uut.ctrl0.state, uut.ir, uut.opcode, uut.wr,
            uut.data_e, uut.sel, uut.addr, uut.data_in_out, uut.data_reg,
            data_out, uut.mem0.mem[7], uut.ctrl0.ld_ac, uut.alu0.out);   
    end
    // Dump waveform for Cadence
    initial begin
        $dumpfile("sim/waveform.vcd");
        $dumpvars(0, tb_risc_cpu);
    end

endmodule

sim/waveform.vcd
$date
	Mon May 05 11:43:02 2025
$end
$version
	Icarus Verilog
$end
$timescale
	1ps
$end
$scope module tb_risc_cpu $end
$var wire 8 ! data_out [7:0] $end
$var reg 1 " clk $end
$var reg 1 # rst $end
$scope module uut $end
$var wire 5 $ addr [4:0] $end
$var wire 8 % alu_inB [7:0] $end
$var wire 8 & alu_out [7:0] $end
$var wire 1 ' clk $end
$var wire 1 ( data_e $end
$var wire 8 ) data_in [7:0] $end
$var wire 8 * data_in_out [7:0] $end
$var wire 8 + data_out [7:0] $end
$var wire 1 , halt $end
$var wire 1 - inc_pc $end
$var wire 1 . ld_ac $end
$var wire 1 / ld_ir $end
$var wire 1 0 ld_pc $end
$var wire 8 1 mem_out [7:0] $end
$var wire 3 2 opcode [2:0] $end
$var wire 5 3 pc [4:0] $end
$var wire 1 4 rd $end
$var wire 8 5 reg_out [7:0] $end
$var wire 1 6 rst $end
$var wire 1 7 sel $end
$var wire 1 8 wr $end
$var wire 1 9 zero $end
$var reg 8 : data_reg [7:0] $end
$var reg 8 ; ir [7:0] $end
$scope module pc0 $end
$var wire 1 ' clk $end
$var wire 1 - inc_pc $end
$var wire 1 0 load $end
$var wire 5 < load_val [4:0] $end
$var wire 1 6 rst $end
$var reg 5 = pc [4:0] $end
$upscope $end
$scope module mux0 $end
$var wire 5 > addr [4:0] $end
$var wire 5 ? inst_addr [4:0] $end
$var wire 5 @ op_addr [4:0] $end
$var wire 1 7 sel $end
$upscope $end
$scope module alu0 $end
$var wire 8 A inA [7:0] $end
$var wire 8 B inB [7:0] $end
$var wire 1 9 is_zero $end
$var wire 3 C opcode [2:0] $end
$var reg 8 D out [7:0] $end
$upscope $end
$scope module ctrl0 $end
$var wire 1 ' clk $end
$var wire 3 E opcode [2:0] $end
$var wire 1 6 rst $end
$var wire 1 9 zero $end
$var reg 1 F data_e $end
$var reg 1 G halt $end
$var reg 1 H inc_pc $end
$var reg 1 I ld_ac $end
$var reg 1 J ld_ir $end
$var reg 1 K ld_pc $end
$var reg 1 L rd $end
$var reg 1 M sel $end
$var reg 3 N state [2:0] $end
$var reg 1 O wr $end
$upscope $end
$scope module reg0 $end
$var wire 1 ' clk $end
$var wire 8 P in [7:0] $end
$var wire 1 . load $end
$var wire 1 6 rst $end
$var reg 8 Q out [7:0] $end
$upscope $end
$scope module mem0 $end
$var wire 5 R addr [4:0] $end
$var wire 1 ' clk $end
$var wire 8 S data_in [7:0] $end
$var wire 1 4 rd $end
$var wire 1 8 wr $end
$var reg 8 T data_out [7:0] $end
$upscope $end
$upscope $end
$upscope $end
$enddefinitions $end
#0
$dumpvars
bx T
b0 S
b0 R
b0 Q
b0 P
0O
b0 N
1M
0L
0K
0J
0I
0H
0G
0F
b101 E
b0 D
b101 C
b0 B
b0 A
b0 @
b0 ?
b0 >
b0 =
bx <
b10100000 ;
b0 :
19
08
17
16
b0 5
04
b0 3
b101 2
bx 1
00
0/
0.
0-
0,
b0 +
b0 *
b0 )
0(
0'
b0 &
b0 %
b0 $
1#
0"
b0 !
$end
#5000
1"
1'
#10000
0"
0'
#15000
1"
1'
#20000
0"
0'
0#
06
#25000
1L
14
1M
17
b1 N
1"
1'
#30000
0"
0'
#35000
b101 <
1J
1/
1L
14
1M
17
b10100101 T
b10100101 1
b10 N
1"
1'
#40000
0"
0'
#45000
b101 $
b101 >
b101 R
b101 @
0J
0/
0L
04
0M
07
b10100101 ;
b11 N
1"
1'
#50000
0"
0'
#55000
1L
14
b100 N
1"
1'
#60000
0"
0'
#65000
b10000 <
b10100101 D
09
b10100101 &
b10100101 P
0L
04
b10000 T
b10000 1
b10100101 :
b10100101 %
b10100101 B
b101 N
1"
1'
#70000
0"
0'
#75000
1I
1.
b110 N
1"
1'
#80000
0"
0'
#85000
1H
1-
b10100101 Q
b10100101 5
b10100101 A
b10100101 !
b10100101 +
0I
0.
b111 N
1"
1'
#90000
0"
0'
#95000
b1 $
b1 >
b1 R
1M
17
0H
0-
b1 =
b1 3
b1 ?
b0 N
1"
1'
#100000
0"
0'
#105000
1L
14
1M
17
b1 N
1"
1'
#110000
0"
0'
#115000
b110 <
1J
1/
1L
14
1M
17
b1000110 T
b1000110 1
b10 N
1"
1'
#120000
0"
0'
#125000
b1001010 D
b1001010 &
b1001010 P
b110 $
b110 >
b110 R
b110 @
b10 2
b10 C
b10 E
0J
0/
0L
04
0M
07
b1000110 ;
b11 N
1"
1'
#130000
0"
0'
#135000
1L
14
b100 N
1"
1'
#140000
0"
0'
#145000
b0 <
b11101011 D
b11101011 &
b11101011 P
0L
04
b100000 T
b100000 1
b1000110 :
b1000110 %
b1000110 B
b101 N
1"
1'
#150000
0"
0'
#155000
1I
1.
b110 N
1"
1'
#160000
0"
0'
#165000
b110001 D
b110001 &
b110001 P
1H
1-
b11101011 Q
b11101011 5
b11101011 A
b11101011 !
b11101011 +
0I
0.
b111 N
1"
1'
#170000
0"
0'
#175000
b10 $
b10 >
b10 R
1M
17
0H
0-
b10 =
b10 3
b10 ?
b0 N
1"
1'
#180000
0"
0'
#185000
1L
14
1M
17
b1 N
1"
1'
#190000
0"
0'
#195000
b111 <
1J
1/
1L
14
1M
17
b11000111 T
b11000111 1
b10 N
1"
1'
#200000
0"
0'
#205000
b11101011 D
b11101011 &
b11101011 P
b111 $
b111 >
b111 R
b111 @
b110 2
b110 C
b110 E
0J
0/
0L
04
0M
07
b11000111 ;
b11 N
1"
1'
#210000
0"
0'
#215000
1L
14
b100 N
1"
1'
#220000
0"
0'
#225000
b0 <
0L
04
b0 T
b0 1
b11000111 :
b11000111 %
b11000111 B
b101 N
1"
1'
#230000
0"
0'
#235000
b11101011 )
b11101011 S
b11101011 *
1F
1(
1O
18
b110 N
1"
1'
#240000
0"
0'
#245000
b0 )
b0 S
b0 *
1H
1-
0F
0(
0O
08
b111 N
1"
1'
#250000
0"
0'
#255000
b11 $
b11 >
b11 R
1M
17
0H
0-
b11 =
b11 3
b11 ?
b0 N
1"
1'
#260000
0"
0'
#265000
1L
14
1M
17
b1 N
1"
1'
#270000
0"
0'
#275000
1J
1/
1L
14
1M
17
b10 N
1"
1'
#280000
0"
0'
#285000
1G
1,
b0 $
b0 >
b0 R
b0 @
b0 2
b0 C
b0 E
0J
0/
0L
04
0M
07
b0 ;
b11 N
1"
1'
#290000
0"
0'
#295000
1L
14
1G
1,
b100 N
1"
1'
#300000
0"
0'
#305000
b101 <
1G
1,
0L
04
b10100101 T
b10100101 1
b0 :
b0 %
b0 B
b101 N
1"
1'
#310000
0"
0'
#315000
1G
1,
b110 N
1"
1'
#320000
0"
0'
#325000
1G
1,
b111 N
1"
1'
