src/defines.v
// File: src/defines.v
// Description: Constants for RISC CPU opcodes and controller states

`ifndef DEFINES_V
`define DEFINES_V

// Opcode definitions (3-bit)
`define OPCODE_HLT  3'b000  // Halt
`define OPCODE_SKZ  3'b001  // Skip if zero
`define OPCODE_ADD  3'b010  // Add
`define OPCODE_AND  3'b011  // Bitwise AND
`define OPCODE_XOR  3'b100  // Bitwise XOR
`define OPCODE_LDA  3'b101  // Load Accumulator
`define OPCODE_STO  3'b110  // Store Accumulator
`define OPCODE_JMP  3'b111  // Jump

// Controller state encodings (3-bit)
`define STATE_INST_ADDR  3'd0  // Instruction address
`define STATE_INST_FETCH 3'd1  // Instruction fetch
`define STATE_INST_LOAD  3'd2  // Instruction load
//`define STATE_IDLE       3'd3  // Idle
`define STATE_OP_ADDR    3'd3  // Operand address
`define STATE_OP_FETCH   3'd4  // Operand fetch
`define STATE_ALU_OP     3'd5  // ALU operation
`define STATE_STORE      3'd6  // Store
`define STATE_NEXT       3'd7   
`endif

src/memory.v
// File: src/memory.v
// Description: 32x8-bit Memory for RISC CPU
`timescale 1ns/1ps

module memory (
    input  wire        clk,
    input  wire [4:0]  addr,
    input  wire [7:0]  data_in,
    output reg  [7:0]  data_out,
    input  wire        rd,
    input  wire        wr
);
    reg [7:0] mem [0:31];

    // Combinational read
    always @(*) begin
        if (rd)
            data_out = mem[addr];
        else
            data_out = 8'b0;
    end

    // Synchronous write
    always @(posedge clk) begin
        if (wr)
            mem[addr] <= data_in;
    end
endmodule

src/register.v
// File: src/register.v
// Description: 8-bit Accumulator for RISC CPU
`timescale 1ns/1ps

module register (
    input wire clk,
    input wire rst,
    input wire load,
    input wire [7:0] in,
    output reg [7:0] out
);
    always @(posedge clk or posedge rst) begin
        if (rst)
            out <= 8'b0;
        else if (load)
            out <= in;
    end
endmodule

src/controller.v
// File: src/controller.v
// Description: Controller for RISC CPU with 8 states
// Includes defines.v for opcode and state constants

`timescale 1ns/1ps
`include "src/defines.v"

module controller (
    input wire        clk,
    input wire        rst,
    input wire [2:0]  opcode,
    input wire        zero,
    output reg        sel,
    output reg        rd,
    output reg        ld_ir,
    output reg        halt,
    output reg [1:0]  inc_pc,
    output reg        ld_ac,
    output reg        ld_pc,
    output reg        wr,
    output reg        data_e,
    output reg [2:0] state
);

    reg skip_next;

    // Sequential logic (partial)
    always @(posedge clk or posedge rst) begin
        if (rst) begin
            sel <= 0; rd <= 0; ld_ir <= 0; halt <= 0;
            inc_pc <= 0; ld_ac <= 0; ld_pc <= 0; wr <= 0; data_e <= 0;
            skip_next <= 0;
            state <= `STATE_INST_ADDR;
        end else if (halt) begin
            rd <= 0; ld_ir <= 0; inc_pc <= 0;
        end else begin
            case (state)
                `STATE_INST_ADDR: state <= `STATE_INST_FETCH;
                `STATE_INST_FETCH: state <= `STATE_INST_LOAD;
                `STATE_INST_LOAD: state <= `STATE_OP_ADDR;
                `STATE_OP_ADDR: state <= `STATE_OP_FETCH;
                `STATE_OP_FETCH: state <= `STATE_ALU_OP;
                `STATE_ALU_OP: state <= `STATE_STORE;
                `STATE_STORE: state <= `STATE_NEXT;
                `STATE_NEXT: begin
                    if (skip_next) state <= `STATE_INST_ADDR; // Skip next instruction
                    else state <= `STATE_INST_ADDR; // Normal progression
                end
                default: state <= `STATE_INST_ADDR; // Reset to initial state if undefined
            endcase

            // Handle opcode-specific logic
            case (state)
                `STATE_ALU_OP: begin
                    ld_ac <= (opcode == `OPCODE_ADD || opcode == `OPCODE_AND ||
                            opcode == `OPCODE_XOR || opcode == `OPCODE_LDA);
                    skip_next <= (opcode == `OPCODE_SKZ && zero);
                    ld_pc <= (opcode == `OPCODE_JMP);
                    if (opcode == `OPCODE_SKZ)
                        $display("SKZ: zero=%b, skip_next=%b at time %t", zero, (opcode == `OPCODE_SKZ && zero), $time);
                end
                `STATE_STORE: begin
                    ld_ac <= 0;
                end
                default: begin
                    ld_ac <= 0;
                    skip_next <= 0;
                end
            endcase
        end
    end

    // Combinational logic (partial)
    always @(*) begin
        sel = 0; rd = 0; ld_ir = 0; halt = 0; inc_pc = 0;
        ld_pc = 0; wr = 0; data_e = 0;

        halt = (opcode == `OPCODE_HLT);

        case (state)
            `STATE_INST_ADDR: begin
                sel = 1;
            end
            `STATE_INST_FETCH: begin
                sel = 1;
                rd = 1;
            end
            `STATE_INST_LOAD: begin
                sel = 1;
                rd = 1;
                ld_ir = 1;
            end
            `STATE_OP_ADDR: begin
                sel = 0;
            end
            `STATE_OP_FETCH: begin
                sel = 0;
                rd = 1;
            end
            `STATE_ALU_OP: begin
                ld_pc = (opcode == `OPCODE_JMP);
            end
            `STATE_STORE: begin
                wr = (opcode == `OPCODE_STO);
                data_e = (opcode == `OPCODE_STO);
                sel = 0;
            end
            `STATE_NEXT: begin
                if (skip_next) begin
                    inc_pc = 2;
                    $display("SKZ: Skipping next instruction, inc_pc set to 2 at time %t", $time);
                end else if (!halt) begin
                    inc_pc = 1; // Ensure PC increments for valid instructions
                end
            end
            default: begin
                halt = 1; // Halt on undefined state as a fallback
            end
        endcase
    end

endmodule

src/alu.v
// File: src/alu.v
// Description: ALU for RISC CPU with 8 operations
// Includes defines.v for opcode constants

`include "src/defines.v"

module alu (
    input  wire [2:0] opcode,    // 3-bit opcode
    input  wire [7:0]  inA,       // 8-bit input A (Accumulator)
    input  wire [7:0]  inB,       // 8-bit input B (Memory)
    output reg  [7:0]  out,       // 8-bit output
    output wire        is_zero    // Asynchronous zero flag
);
    // Combinational ALU operations
    always @(*) begin
        case (opcode)
            `OPCODE_HLT:  out = inA;                // Halt: pass inA
            `OPCODE_SKZ:  out = inA;                // Skip if zero: pass inA
            `OPCODE_ADD:  out = inA + inB;          // Add
            `OPCODE_AND:  out = inA & inB;          // Bitwise AND
            `OPCODE_XOR:  out = inA ^ inB;          // Bitwise XOR
            `OPCODE_LDA:  out = inB;                // Load Accumulator
            `OPCODE_STO:  out = inA;                // Store: pass inA
            `OPCODE_JMP:  out = inA;                // Jump: pass inA
            default:      out = 8'b0;               // Default: 0
        endcase
	is_zero = (out == 8'b0);
    end

endmodule

src/address_mux.v
// File: src/address_mux.v
// Description: 5-bit Address Mux for RISC CPU
`timescale 1ns/1ps

module address_mux #(
    parameter WIDTH = 5
) (
    input  wire             sel,        // Select: 1=instruction, 0=operand
    input  wire [WIDTH-1:0] inst_addr,  // Instruction address (from PC)
    input  wire [WIDTH-1:0] op_addr,    // Operand address (from instruction)
    output wire [WIDTH-1:0] addr        // Selected address
);

    assign addr = sel ? inst_addr : op_addr;

endmodule

src/program_counter.v
// File: src/program_counter.v
// Description: 5-bit Program Counter for RISC CPU
`timescale 1ns/1ps

module program_counter (
    input  wire        clk,
    input  wire        rst,
    input  wire        load,
    input  wire [1:0]  inc_pc,  // 2 bits: 0 = no increment, 1 = +1, 2 = +2
    input  wire [4:0]  load_val,
    output reg  [4:0]  pc
);

    always @(posedge clk or posedge rst) begin
        if (rst)
            pc <= 0;
        else if (load)
            pc <= load_val;
        else if (inc_pc == 2)
            pc <= pc + 2;  // Skip next instruction
        else if (inc_pc == 1)
            pc <= pc + 1;  // Normal increment
    end
endmodule

src/risc_cpu.v
// File: src/risc_cpu.v
// Description: Top-level RISC CPU module
// Includes defines.v for opcode constants
`timescale 1ns/1ps

`include "src/defines.v"
`include "src/program_counter.v"
`include "src/address_mux.v"
`include "src/alu.v"
`include "src/controller.v"
`include "src/register.v"
`include "src/memory.v"

module risc_cpu (
    input  wire        clk,        // Clock input
    input  wire        rst,        // Reset input
    output wire [7:0]  data_out,   // Accumulator output
    output wire [7:0]  data_in_out // Expose data_in for monitoring
);

    // Internal signals
    wire [4:0] pc;                // Program Counter
    wire [4:0] addr;              // Memory address
    wire [7:0] alu_out;           // ALU output
    wire [7:0] reg_out;           // Accumulator output
    wire [7:0] mem_out;           // Memory output
    wire [2:0] opcode;            // 3-bit opcode
    wire sel, rd, ld_ir, halt, ld_ac, ld_pc, wr, data_e, zero;

    // Add data register to latch memory output
    reg [7:0] data_reg;
    wire [7:0] alu_inB;           // ALU input B (from data_reg)

    // Module instantiations
    wire [1:0] inc_pc;  

    program_counter pc0 (
        .clk(clk),
        .rst(rst),
        .load(ld_pc),
        .inc_pc(inc_pc),  // Now 2 bits
        .load_val(ir[4:0]),
        .pc(pc)
    );
    always @(posedge clk or posedge rst) begin
        if (rst)
            ir <= 8'b10100000;  // Non-HLT opcode
        else if (ld_ir) begin
            ir <= mem_out;
            $display("IR updated to %h (ir[4:0]=%b) at time %t", mem_out, mem_out[4:0], $time);
        end
    end

    address_mux mux0 (
        .sel(sel),
        .inst_addr(pc),
        .op_addr(ir[4:0]),
        .addr(addr)
    );

    alu alu0 (
        .opcode(opcode),
        .inA(reg_out),
        .inB(alu_inB),
        .out(alu_out),
        .is_zero(zero)
    );
    always @(zero) $display("Zero signal updated to %b at time %t", zero, $time);

    controller ctrl0 (
        .clk(clk),
        .rst(rst),
        .opcode(opcode),
        .zero(zero),
        .sel(sel),
        .rd(rd),
        .ld_ir(ld_ir),
        .halt(halt),
        .inc_pc(inc_pc),
        .ld_ac(ld_ac),
        .ld_pc(ld_pc),
        .wr(wr),
        .data_e(data_e),
        .state(state)  // Add state output
    );

    register reg0 (
        .clk(clk),
        .rst(rst),
        .load(ld_ac),
        .in(alu_out),
        .out(reg_out)
    );
    //debug accumulator
    always @(posedge clk) begin
        if (ld_ac)
            $display("Accumulator updated to %h at time %t", alu_out, $time);
    end


    memory mem0 (
        .clk(clk),
        .addr(addr),
        .data_in(data_in),
        .data_out(mem_out),
        .rd(rd),
        .wr(wr)
    );

    // Instruction register
    reg [7:0] ir;
    always @(posedge clk or posedge rst) begin
        if (rst)
            ir <= 8'b10100000;  // Non-HLT opcode
        else if (ld_ir)
            ir <= mem_out;
    end

    // Extract opcode
    assign opcode = ir[7:5];
    assign data_out = reg_out;

    // Data input for memory
    wire [7:0] data_in = data_e ? reg_out : 8'b0;
    assign data_in_out = data_in;

    // Latch memory data one cycle after STATE_OP_FETCH
    reg [2:0] prev_state;
    always @(posedge clk or posedge rst) begin
        if (rst) begin
            data_reg <= 8'b0;
            prev_state <= 0;
        end else begin
            prev_state <= state;
            if (state == `STATE_OP_FETCH)  // Capture during STATE_OP_FETCH
                data_reg <= mem_out;
        end
    end

    //debug data reg
    always @(posedge clk) begin
        if (state == `STATE_OP_FETCH)
            $display("STATE_OP_FETCH: mem_out=%h, Data_reg=%h at time %t", mem_out, data_reg, $time);
    end

    // Assign ALU input B from data_reg
    assign alu_inB = data_reg;

    // Local state wire (if not directly accessible)
    wire [2:0] state;

endmodule

tb/risc_cpu_tb.v

// Description: Testbench for RISC CPU module
`timescale 1ns/1ps
`include "src/risc_cpu.v"

module tb_risc_cpu;

    // Inputs
    reg clk;
    reg rst;

    // Outputs
    wire [7:0] data_out;

    // Instantiate RISC CPU
    risc_cpu uut (
        .clk(clk),
        .rst(rst),
        .data_out(data_out)
    );

    // Clock generation
    initial begin
        clk = 0;
        forever #5 clk = ~clk;  // 10ns period (100 MHz)
    end

    // Test stimulus
    initial begin
        // Reset
        rst = 1;
        #20;
        rst = 0;

        // Load memory with test1.mem or test2.mem
        //$readmemb("tb/test_programs/test1.mem", uut.mem0.mem);  // For test1.mem
        $readmemh("tb/test_programs/test2.mem", uut.mem0.mem);  // For test2.mem use hex format
        
        // Debug: Print memory contents to verify initialization
        // #10;
        // integer i;
        // for (i = 0; i < 10; i = i + 1) begin
        //     $display("Mem[%d] = %h at time %t", i, uut.mem0.mem[i], $time);
        // end


        // Run simulation for a fixed time
        #1000;

        // Check results
        $display("Final Accumulator value: %h", data_out);
        $display("Memory at address 7: %h", uut.mem0.mem[7]);  // For test1.mem
        $finish;
    end

    //debug monitor
    initial begin
        $monitor("Time=%0t rst=%b clk=%b PC=%d State=%d IR=%h Opcode=%b Wr=%b Data_e=%b Sel=%b Addr=%h Data_in=%h Data_reg=%h Accumulator=%h Mem[7]=%h Ld_ac=%b Alu_out=%h",
            $time, rst, clk, uut.pc, uut.ctrl0.state, uut.ir, uut.opcode, uut.wr,
            uut.data_e, uut.sel, uut.addr, uut.data_in_out, uut.data_reg,
            data_out, uut.mem0.mem[7], uut.ctrl0.ld_ac, uut.alu0.out);   
    end
    
    // Dump waveform for Cadence
    initial begin
        $dumpfile("sim/waveform.vcd");
        $dumpvars(0, tb_risc_cpu);
    end

endmodule

sim/waveform.vcd
$date
	Mon May 05 13:53:12 2025
$end
$version
	Icarus Verilog
$end
$timescale
	1ps
$end
$scope module tb_risc_cpu $end
$var wire 8 ! data_out [7:0] $end
$var reg 1 " clk $end
$var reg 1 # rst $end
$scope module uut $end
$var wire 5 $ addr [4:0] $end
$var wire 8 % alu_inB [7:0] $end
$var wire 8 & alu_out [7:0] $end
$var wire 1 ' clk $end
$var wire 1 ( data_e $end
$var wire 8 ) data_in [7:0] $end
$var wire 8 * data_in_out [7:0] $end
$var wire 8 + data_out [7:0] $end
$var wire 1 , halt $end
$var wire 2 - inc_pc [1:0] $end
$var wire 1 . ld_ac $end
$var wire 1 / ld_ir $end
$var wire 1 0 ld_pc $end
$var wire 8 1 mem_out [7:0] $end
$var wire 3 2 opcode [2:0] $end
$var wire 5 3 pc [4:0] $end
$var wire 1 4 rd $end
$var wire 8 5 reg_out [7:0] $end
$var wire 1 6 rst $end
$var wire 1 7 sel $end
$var wire 3 8 state [2:0] $end
$var wire 1 9 wr $end
$var wire 1 : zero $end
$var reg 8 ; data_reg [7:0] $end
$var reg 8 < ir [7:0] $end
$var reg 3 = prev_state [2:0] $end
$scope module pc0 $end
$var wire 1 ' clk $end
$var wire 2 > inc_pc [1:0] $end
$var wire 1 0 load $end
$var wire 5 ? load_val [4:0] $end
$var wire 1 6 rst $end
$var reg 5 @ pc [4:0] $end
$upscope $end
$scope module mux0 $end
$var wire 5 A addr [4:0] $end
$var wire 5 B inst_addr [4:0] $end
$var wire 5 C op_addr [4:0] $end
$var wire 1 7 sel $end
$upscope $end
$scope module alu0 $end
$var wire 8 D inA [7:0] $end
$var wire 8 E inB [7:0] $end
$var wire 1 : is_zero $end
$var wire 3 F opcode [2:0] $end
$var reg 8 G out [7:0] $end
$upscope $end
$scope module ctrl0 $end
$var wire 1 ' clk $end
$var wire 3 H opcode [2:0] $end
$var wire 1 6 rst $end
$var wire 1 : zero $end
$var reg 1 I data_e $end
$var reg 1 J halt $end
$var reg 2 K inc_pc [1:0] $end
$var reg 1 L ld_ac $end
$var reg 1 M ld_ir $end
$var reg 1 N ld_pc $end
$var reg 1 O rd $end
$var reg 1 P sel $end
$var reg 1 Q skip_next $end
$var reg 3 R state [2:0] $end
$var reg 1 S wr $end
$upscope $end
$scope module reg0 $end
$var wire 1 ' clk $end
$var wire 8 T in [7:0] $end
$var wire 1 . load $end
$var wire 1 6 rst $end
$var reg 8 U out [7:0] $end
$upscope $end
$scope module mem0 $end
$var wire 5 V addr [4:0] $end
$var wire 1 ' clk $end
$var wire 8 W data_in [7:0] $end
$var wire 1 4 rd $end
$var wire 1 9 wr $end
$var reg 8 X data_out [7:0] $end
$upscope $end
$upscope $end
$upscope $end
$enddefinitions $end
#0
$dumpvars
b0 X
b0 W
b0 V
b0 U
b0 T
0S
b0 R
0Q
1P
0O
0N
0M
0L
b0 K
0J
0I
b101 H
b0 G
b101 F
b0 E
b0 D
b0 C
b0 B
b0 A
b0 @
b0 ?
b0 >
b0 =
b10100000 <
b0 ;
1:
09
b0 8
17
16
b0 5
04
b0 3
b101 2
b0 1
00
0/
0.
b0 -
0,
b0 +
b0 *
b0 )
0(
0'
b0 &
b0 %
b0 $
1#
0"
b0 !
$end
#5000
1"
1'
#10000
0"
0'
#15000
1"
1'
#20000
0"
0'
0#
06
#25000
b10100101 X
b10100101 1
1O
14
1P
17
b1 R
b1 8
1"
1'
#30000
0"
0'
#35000
1M
1/
1O
14
1P
17
b10 R
b10 8
b1 =
1"
1'
#40000
0"
0'
#45000
b0 X
b0 1
b101 $
b101 A
b101 V
b101 ?
b101 C
0M
0/
0O
04
0P
07
b10 =
b10100101 <
b11 R
b11 8
1"
1'
#50000
0"
0'
#55000
b11111111 X
b11111111 1
1O
14
b100 R
b100 8
b11 =
1"
1'
#60000
0"
0'
#65000
b0 X
b0 1
b11111111 G
0:
b11111111 &
b11111111 T
0O
04
b11111111 ;
b11111111 %
b11111111 E
b100 =
b101 R
b101 8
1"
1'
#70000
0"
0'
#75000
1L
1.
b110 R
b110 8
b101 =
1"
1'
#80000
0"
0'
#85000
b1 K
b1 -
b1 >
b110 =
b11111111 U
b11111111 5
b11111111 D
b11111111 !
b11111111 +
0L
0.
b111 R
b111 8
1"
1'
#90000
0"
0'
#95000
b1 $
b1 A
b1 V
1P
17
b0 K
b0 -
b0 >
b1 @
b1 3
b1 B
b0 R
b0 8
b111 =
1"
1'
#100000
0"
0'
#105000
b10000110 X
b10000110 1
1O
14
1P
17
b0 =
b1 R
b1 8
1"
1'
#110000
0"
0'
#115000
1M
1/
1O
14
1P
17
b10 R
b10 8
b1 =
1"
1'
#120000
0"
0'
#125000
b0 G
1:
b0 &
b0 T
b0 X
b0 1
b110 $
b110 A
b110 V
b110 ?
b110 C
b100 2
b100 F
b100 H
0M
0/
0O
04
0P
07
b10 =
b10000110 <
b11 R
b11 8
1"
1'
#130000
0"
0'
#135000
b11111111 X
b11111111 1
1O
14
b100 R
b100 8
b11 =
1"
1'
#140000
0"
0'
#145000
b0 X
b0 1
0O
04
b100 =
b101 R
b101 8
1"
1'
#150000
0"
0'
#155000
1L
1.
b110 R
b110 8
b101 =
1"
1'
#160000
0"
0'
#165000
b11111111 G
0:
b11111111 &
b11111111 T
b1 K
b1 -
b1 >
b110 =
b0 U
b0 5
b0 D
b0 !
b0 +
0L
0.
b111 R
b111 8
1"
1'
#170000
0"
0'
#175000
b10 $
b10 A
b10 V
1P
17
b0 K
b0 -
b0 >
b10 @
b10 3
b10 B
b0 R
b0 8
b111 =
1"
1'
#180000
0"
0'
#185000
b100000 X
b100000 1
1O
14
1P
17
b0 =
b1 R
b1 8
1"
1'
#190000
0"
0'
#195000
1M
1/
1O
14
1P
17
b10 R
b10 8
b1 =
1"
1'
#200000
0"
0'
#205000
b0 G
1:
b0 &
b0 T
b0 X
b0 1
b0 $
b0 A
b0 V
b0 ?
b0 C
b1 2
b1 F
b1 H
0M
0/
0O
04
0P
07
b10 =
b100000 <
b11 R
b11 8
1"
1'
#210000
0"
0'
#215000
b10100101 X
b10100101 1
1O
14
b100 R
b100 8
b11 =
1"
1'
#220000
0"
0'
#225000
b0 X
b0 1
0O
04
b10100101 ;
b10100101 %
b10100101 E
b100 =
b101 R
b101 8
1"
1'
#230000
0"
0'
#235000
1Q
b110 R
b110 8
b101 =
1"
1'
#240000
0"
0'
#245000
b10 K
b10 -
b10 >
b110 =
b111 R
b111 8
1"
1'
#250000
0"
0'
#255000
b100 $
b100 A
b100 V
1P
17
b0 K
b0 -
b0 >
b100 @
b100 3
b100 B
0Q
b0 R
b0 8
b111 =
1"
1'
#260000
0"
0'
#265000
b1100111 X
b1100111 1
1O
14
1P
17
b0 =
b1 R
b1 8
1"
1'
#270000
0"
0'
#275000
1M
1/
1O
14
1P
17
b10 R
b10 8
b1 =
1"
1'
#280000
0"
0'
#285000
b0 X
b0 1
b111 $
b111 A
b111 V
b111 ?
b111 C
b11 2
b11 F
b11 H
0M
0/
0O
04
0P
07
b10 =
b1100111 <
b11 R
b11 8
1"
1'
#290000
0"
0'
#295000
b10101010 X
b10101010 1
1O
14
b100 R
b100 8
b11 =
1"
1'
#300000
0"
0'
#305000
b0 X
b0 1
0O
04
b10101010 ;
b10101010 %
b10101010 E
b100 =
b101 R
b101 8
1"
1'
#310000
0"
0'
#315000
1L
1.
b110 R
b110 8
b101 =
1"
1'
#320000
0"
0'
#325000
b1 K
b1 -
b1 >
b110 =
0L
0.
b111 R
b111 8
1"
1'
#330000
0"
0'
#335000
b101 $
b101 A
b101 V
1P
17
b0 K
b0 -
b0 >
b101 @
b101 3
b101 B
b0 R
b0 8
b111 =
1"
1'
#340000
0"
0'
#345000
b11111111 X
b11111111 1
1O
14
1P
17
b0 =
b1 R
b1 8
1"
1'
#350000
0"
0'
#355000
1M
1/
1O
14
1P
17
b10 R
b10 8
b1 =
1"
1'
#360000
0"
0'
#365000
b0 X
b0 1
b11111 $
b11111 A
b11111 V
b11111 ?
b11111 C
b111 2
b111 F
b111 H
0M
0/
0O
04
0P
07
b10 =
b11111111 <
b11 R
b11 8
1"
1'
#370000
0"
0'
#375000
bx X
bx 1
1O
14
b100 R
b100 8
b11 =
1"
1'
#380000
0"
0'
#385000
b0 X
b0 1
1N
10
0O
04
bx ;
bx %
bx E
b100 =
b101 R
b101 8
1"
1'
#390000
0"
0'
#395000
0N
00
b11111 @
b11111 3
b11111 B
b110 R
b110 8
b101 =
1"
1'
#400000
0"
0'
#405000
b1 K
b1 -
b1 >
b110 =
b111 R
b111 8
1"
1'
#410000
0"
0'
#415000
b0 $
b0 A
b0 V
1P
17
b0 K
b0 -
b0 >
b0 @
b0 3
b0 B
b0 R
b0 8
b111 =
1"
1'
#420000
0"
0'
#425000
b10100101 X
b10100101 1
1O
14
1P
17
b0 =
b1 R
b1 8
1"
1'
#430000
0"
0'
#435000
1M
1/
1O
14
1P
17
b10 R
b10 8
b1 =
1"
1'
#440000
0"
0'
#445000
bx G
x:
bx &
bx T
b0 X
b0 1
b101 $
b101 A
b101 V
b101 ?
b101 C
b101 2
b101 F
b101 H
0M
0/
0O
04
0P
07
b10 =
b10100101 <
b11 R
b11 8
1"
1'
#450000
0"
0'
#455000
b11111111 X
b11111111 1
1O
14
b100 R
b100 8
b11 =
1"
1'
#460000
0"
0'
#465000
b0 X
b0 1
b11111111 G
0:
b11111111 &
b11111111 T
0O
04
b11111111 ;
b11111111 %
b11111111 E
b100 =
b101 R
b101 8
1"
1'
#470000
0"
0'
#475000
1L
1.
b110 R
b110 8
b101 =
1"
1'
#480000
0"
0'
#485000
b1 K
b1 -
b1 >
b110 =
b11111111 U
b11111111 5
b11111111 D
b11111111 !
b11111111 +
0L
0.
b111 R
b111 8
1"
1'
#490000
0"
0'
#495000
b1 $
b1 A
b1 V
1P
17
b0 K
b0 -
b0 >
b1 @
b1 3
b1 B
b0 R
b0 8
b111 =
1"
1'
#500000
0"
0'
#505000
b10000110 X
b10000110 1
1O
14
1P
17
b0 =
b1 R
b1 8
1"
1'
#510000
0"
0'
#515000
1M
1/
1O
14
1P
17
b10 R
b10 8
b1 =
1"
1'
#520000
0"
0'
#525000
b0 G
1:
b0 &
b0 T
b0 X
b0 1
b110 $
b110 A
b110 V
b110 ?
b110 C
b100 2
b100 F
b100 H
0M
0/
0O
04
0P
07
b10 =
b10000110 <
b11 R
b11 8
1"
1'
#530000
0"
0'
#535000
b11111111 X
b11111111 1
1O
14
b100 R
b100 8
b11 =
1"
1'
#540000
0"
0'
#545000
b0 X
b0 1
0O
04
b100 =
b101 R
b101 8
1"
1'
#550000
0"
0'
#555000
1L
1.
b110 R
b110 8
b101 =
1"
1'
#560000
0"
0'
#565000
b11111111 G
0:
b11111111 &
b11111111 T
b1 K
b1 -
b1 >
b110 =
b0 U
b0 5
b0 D
b0 !
b0 +
0L
0.
b111 R
b111 8
1"
1'
#570000
0"
0'
#575000
b10 $
b10 A
b10 V
1P
17
b0 K
b0 -
b0 >
b10 @
b10 3
b10 B
b0 R
b0 8
b111 =
1"
1'
#580000
0"
0'
#585000
b100000 X
b100000 1
1O
14
1P
17
b0 =
b1 R
b1 8
1"
1'
#590000
0"
0'
#595000
1M
1/
1O
14
1P
17
b10 R
b10 8
b1 =
1"
1'
#600000
0"
0'
#605000
b0 G
1:
b0 &
b0 T
b0 X
b0 1
b0 $
b0 A
b0 V
b0 ?
b0 C
b1 2
b1 F
b1 H
0M
0/
0O
04
0P
07
b10 =
b100000 <
b11 R
b11 8
1"
1'
#610000
0"
0'
#615000
b10100101 X
b10100101 1
1O
14
b100 R
b100 8
b11 =
1"
1'
#620000
0"
0'
#625000
b0 X
b0 1
0O
04
b10100101 ;
b10100101 %
b10100101 E
b100 =
b101 R
b101 8
1"
1'
#630000
0"
0'
#635000
1Q
b110 R
b110 8
b101 =
1"
1'
#640000
0"
0'
#645000
b10 K
b10 -
b10 >
b110 =
b111 R
b111 8
1"
1'
#650000
0"
0'
#655000
b100 $
b100 A
b100 V
1P
17
b0 K
b0 -
b0 >
b100 @
b100 3
b100 B
0Q
b0 R
b0 8
b111 =
1"
1'
#660000
0"
0'
#665000
b1100111 X
b1100111 1
1O
14
1P
17
b0 =
b1 R
b1 8
1"
1'
#670000
0"
0'
#675000
1M
1/
1O
14
1P
17
b10 R
b10 8
b1 =
1"
1'
#680000
0"
0'
#685000
b0 X
b0 1
b111 $
b111 A
b111 V
b111 ?
b111 C
b11 2
b11 F
b11 H
0M
0/
0O
04
0P
07
b10 =
b1100111 <
b11 R
b11 8
1"
1'
#690000
0"
0'
#695000
b10101010 X
b10101010 1
1O
14
b100 R
b100 8
b11 =
1"
1'
#700000
0"
0'
#705000
b0 X
b0 1
0O
04
b10101010 ;
b10101010 %
b10101010 E
b100 =
b101 R
b101 8
1"
1'
#710000
0"
0'
#715000
1L
1.
b110 R
b110 8
b101 =
1"
1'
#720000
0"
0'
#725000
b1 K
b1 -
b1 >
b110 =
0L
0.
b111 R
b111 8
1"
1'
#730000
0"
0'
#735000
b101 $
b101 A
b101 V
1P
17
b0 K
b0 -
b0 >
b101 @
b101 3
b101 B
b0 R
b0 8
b111 =
1"
1'
#740000
0"
0'
#745000
b11111111 X
b11111111 1
1O
14
1P
17
b0 =
b1 R
b1 8
1"
1'
#750000
0"
0'
#755000
1M
1/
1O
14
1P
17
b10 R
b10 8
b1 =
1"
1'
#760000
0"
0'
#765000
b0 X
b0 1
b11111 $
b11111 A
b11111 V
b11111 ?
b11111 C
b111 2
b111 F
b111 H
0M
0/
0O
04
0P
07
b10 =
b11111111 <
b11 R
b11 8
1"
1'
#770000
0"
0'
#775000
bx X
bx 1
1O
14
b100 R
b100 8
b11 =
1"
1'
#780000
0"
0'
#785000
b0 X
b0 1
1N
10
0O
04
bx ;
bx %
bx E
b100 =
b101 R
b101 8
1"
1'
#790000
0"
0'
#795000
0N
00
b11111 @
b11111 3
b11111 B
b110 R
b110 8
b101 =
1"
1'
#800000
0"
0'
#805000
b1 K
b1 -
b1 >
b110 =
b111 R
b111 8
1"
1'
#810000
0"
0'
#815000
b0 $
b0 A
b0 V
1P
17
b0 K
b0 -
b0 >
b0 @
b0 3
b0 B
b0 R
b0 8
b111 =
1"
1'
#820000
0"
0'
#825000
b10100101 X
b10100101 1
1O
14
1P
17
b0 =
b1 R
b1 8
1"
1'
#830000
0"
0'
#835000
1M
1/
1O
14
1P
17
b10 R
b10 8
b1 =
1"
1'
#840000
0"
0'
#845000
bx G
x:
bx &
bx T
b0 X
b0 1
b101 $
b101 A
b101 V
b101 ?
b101 C
b101 2
b101 F
b101 H
0M
0/
0O
04
0P
07
b10 =
b10100101 <
b11 R
b11 8
1"
1'
#850000
0"
0'
#855000
b11111111 X
b11111111 1
1O
14
b100 R
b100 8
b11 =
1"
1'
#860000
0"
0'
#865000
b0 X
b0 1
b11111111 G
0:
b11111111 &
b11111111 T
0O
04
b11111111 ;
b11111111 %
b11111111 E
b100 =
b101 R
b101 8
1"
1'
#870000
0"
0'
#875000
1L
1.
b110 R
b110 8
b101 =
1"
1'
#880000
0"
0'
#885000
b1 K
b1 -
b1 >
b110 =
b11111111 U
b11111111 5
b11111111 D
b11111111 !
b11111111 +
0L
0.
b111 R
b111 8
1"
1'
#890000
0"
0'
#895000
b1 $
b1 A
b1 V
1P
17
b0 K
b0 -
b0 >
b1 @
b1 3
b1 B
b0 R
b0 8
b111 =
1"
1'
#900000
0"
0'
#905000
b10000110 X
b10000110 1
1O
14
1P
17
b0 =
b1 R
b1 8
1"
1'
#910000
0"
0'
#915000
1M
1/
1O
14
1P
17
b10 R
b10 8
b1 =
1"
1'
#920000
0"
0'
#925000
b0 G
1:
b0 &
b0 T
b0 X
b0 1
b110 $
b110 A
b110 V
b110 ?
b110 C
b100 2
b100 F
b100 H
0M
0/
0O
04
0P
07
b10 =
b10000110 <
b11 R
b11 8
1"
1'
#930000
0"
0'
#935000
b11111111 X
b11111111 1
1O
14
b100 R
b100 8
b11 =
1"
1'
#940000
0"
0'
#945000
b0 X
b0 1
0O
04
b100 =
b101 R
b101 8
1"
1'
#950000
0"
0'
#955000
1L
1.
b110 R
b110 8
b101 =
1"
1'
#960000
0"
0'
#965000
b11111111 G
0:
b11111111 &
b11111111 T
b1 K
b1 -
b1 >
b110 =
b0 U
b0 5
b0 D
b0 !
b0 +
0L
0.
b111 R
b111 8
1"
1'
#970000
0"
0'
#975000
b10 $
b10 A
b10 V
1P
17
b0 K
b0 -
b0 >
b10 @
b10 3
b10 B
b0 R
b0 8
b111 =
1"
1'
#980000
0"
0'
#985000
b100000 X
b100000 1
1O
14
1P
17
b0 =
b1 R
b1 8
1"
1'
#990000
0"
0'
#995000
1M
1/
1O
14
1P
17
b10 R
b10 8
b1 =
1"
1'
#1000000
0"
0'
#1005000
b0 G
1:
b0 &
b0 T
b0 X
b0 1
b0 $
b0 A
b0 V
b0 ?
b0 C
b1 2
b1 F
b1 H
0M
0/
0O
04
0P
07
b10 =
b100000 <
b11 R
b11 8
1"
1'
#1010000
0"
0'
#1015000
b10100101 X
b10100101 1
1O
14
b100 R
b100 8
b11 =
1"
1'
